{
  "publishers": [
    "ladybug-tools"
  ],
  "requires_dist": {
    "dists": [
      "dragonfly-energy",
      "lbt-honeybee"
    ],
    "specifiers": [
      "dragonfly-energy (==1.10.88)",
      "lbt-honeybee (==0.2.275)"
    ]
  },
  "requires_extras": {
    "cli": {
      "dists": [
        "click",
        "dragonfly-schema"
      ],
      "specifiers": [
        "click (==7.1.2); extra=='cli'",
        "dragonfly-schema (==1.6.24); (python_version>='3.6') and extra=='cli'"
      ]
    }
  },
  "requires_python": "",
  "yanked": []
}