{
  "publishers": [
    "autopub",
    "jmayer",
    "neithere"
  ],
  "requires_dist": {
    "dists": [],
    "specifiers": []
  },
  "requires_extras": {
    "cyrillic": {
      "dists": [
        "pytils"
      ],
      "specifiers": [
        "pytils (>=0.2); extra=='cyrillic'"
      ]
    },
    "translitcodec": {
      "dists": [
        "translitcodec"
      ],
      "specifiers": [
        "translitcodec (>=0.3); extra=='translitcodec'"
      ]
    }
  },
  "requires_python": "",
  "yanked": []
}