{
  "publishers": [
    "ladybug-tools"
  ],
  "requires_dist": {
    "dists": [
      "dragonfly-core",
      "honeybee-energy"
    ],
    "specifiers": [
      "dragonfly-core (==1.25.58)",
      "honeybee-energy (==1.62.5)"
    ]
  },
  "requires_extras": {
    "cli": {
      "dists": [
        "click",
        "dragonfly-core"
      ],
      "specifiers": [
        "click (==7.1.2); extra=='cli'",
        "dragonfly-core[cli] (==1.25.56); extra=='cli'"
      ]
    }
  },
  "requires_python": "",
  "yanked": []
}