{
  "publishers": [
    "openstackci"
  ],
  "requires_dist": {
    "dists": [
      "keystoneauth1",
      "oslo.i18n",
      "oslo.utils",
      "pbr",
      "prettytable",
      "requests",
      "simplejson",
      "six",
      "stevedore"
    ],
    "specifiers": [
      "keystoneauth1 (>=3.4.0)",
      "oslo.i18n (>=3.15.3)",
      "oslo.utils (>=3.33.0)",
      "pbr (!=2.1.0,>=2.0.0)",
      "prettytable (<0.8,>=0.7.1)",
      "requests (!=2.20.0,>=2.14.2)",
      "simplejson (>=3.5.1)",
      "six (>=1.10.0)",
      "stevedore (>=1.20.0)"
    ]
  },
  "requires_extras": {},
  "requires_python": ">=3.6",
  "yanked": []
}